parimpar/__init__.py
parimpar/par_impar.py
par_impar-0.1.dist-info/LICENSE.MIT
par_impar-0.1.dist-info/METADATA
par_impar-0.1.dist-info/WHEEL
par_impar-0.1.dist-info/top_level.txt
par_impar-0.1.dist-info/RECORD
