Metadata-Version: 2.1
Name: par_impar
Version: 0.1
Summary: Jogo de Par ou Ímpar em Python
Home-page: https://github.com/seuusuario/par_impar
Author: Seu Nome
Author-email: seuemail@example.com
License-File: LICENSE.MIT
